bible_cli/__init__.py
bible_cli/dataset.json
bible_cli/bible_cli/__init__.py
bible_cli-1.0.3.dist-info/licenses/LICENSE
bible_cli-1.0.3.dist-info/METADATA
bible_cli-1.0.3.dist-info/WHEEL
bible_cli-1.0.3.dist-info/entry_points.txt
bible_cli-1.0.3.dist-info/top_level.txt
bible_cli-1.0.3.dist-info/RECORD
