Metadata-Version: 2.4
Name: bible-cli
Version: 1.0.3
Summary: A command-line interface for reading and searching the Bible
Home-page: https://github.com/wisyhambolu/Bible-Cli
Author: Wisdom Hambolu
Author-email: wisyhambolu@gmail.com
License-Expression: MIT
Classifier: Development Status :: 4 - Beta
Classifier: Environment :: Console
Classifier: Intended Audience :: End Users/Desktop
Classifier: Programming Language :: Python :: 3
Classifier: Programming Language :: Python :: 3.8
Classifier: Programming Language :: Python :: 3.9
Classifier: Programming Language :: Python :: 3.10
Classifier: Programming Language :: Python :: 3.11
Classifier: Programming Language :: Python :: 3.12
Classifier: Topic :: Religion
Requires-Python: >=3.8
License-File: LICENSE
Requires-Dist: rich>=13.7.0
Requires-Dist: rapidfuzz>=3.6.1
Dynamic: author-email
Dynamic: home-page
Dynamic: license-file
Dynamic: requires-python
